cli_bot/__init__.py
cli_bot/bot.py
cli_botx-1.0.0.dist-info/licenses/LICENSE
cli_botx-1.0.0.dist-info/METADATA
cli_botx-1.0.0.dist-info/WHEEL
cli_botx-1.0.0.dist-info/entry_points.txt
cli_botx-1.0.0.dist-info/top_level.txt
cli_botx-1.0.0.dist-info/RECORD
