Metadata-Version: 2.4
Name: cli-botx
Version: 1.0.0
Summary: A simple command-line assistant with calculator, web shortcuts, and task list.
Home-page: https://github.com/yatinannam/cli-bot
Author: Yatin Annam
License: MIT
Requires-Python: >=3.8
License-File: LICENSE
Dynamic: author
Dynamic: description
Dynamic: description-content-type
Dynamic: home-page
Dynamic: license
Dynamic: license-file
Dynamic: requires-python
Dynamic: summary
